api_sentinel_sdk-1.0.0.dist-info/licenses/LICENSE
sentinel/__init__.py
sentinel/errors.py
sentinel/adapters/__init__.py
sentinel/adapters/base.py
sentinel/adapters/openai.py
api_sentinel_sdk-1.0.0.dist-info/METADATA
api_sentinel_sdk-1.0.0.dist-info/WHEEL
api_sentinel_sdk-1.0.0.dist-info/top_level.txt
api_sentinel_sdk-1.0.0.dist-info/RECORD
